notefile/__init__.py
notefile/compress/__init__.py
notefile/compress/tarfile.py
notefile/file/__init__.py
notefile/file/core.py
notefile/system/__init__.py
notefile/system/base.py
notefile/system/lanzou/__init__.py
notefile/system/lanzou/core.py
notefile/system/lanzou/utils.py
notefile-0.0.15.dist-info/METADATA
notefile-0.0.15.dist-info/WHEEL
notefile-0.0.15.dist-info/top_level.txt
notefile-0.0.15.dist-info/RECORD
