Metadata-Version: 2.1
Name: notefile
Version: 0.0.15
Summary: notefile
Home-page: https://github.com/1007530194
Author: niuliangtao
Author-email: 1007530194@qq.com
License: UNKNOWN
Platform: UNKNOWN
Requires-Dist: tqdm
